DSAs/__init__.py
DSAs/sorting/__init__.py
DSAs/sorting/bubblesort.py
DSAs/sorting/cocktailsort.py
DSAs/sorting/combsort.py
DSAs/sorting/heapsort.py
DSAs/sorting/insertionsort.py
DSAs/sorting/selectionsort.py
DSAs/sorting/shellsort.py
DSAs/sorting/util.py
DSAs-0.0.9.dist-info/LICENSE.txt
DSAs-0.0.9.dist-info/METADATA
DSAs-0.0.9.dist-info/WHEEL
DSAs-0.0.9.dist-info/top_level.txt
DSAs-0.0.9.dist-info/RECORD
